README.md
setup.py
posix_pythonic_tool.egg-info/PKG-INFO
posix_pythonic_tool.egg-info/SOURCES.txt
posix_pythonic_tool.egg-info/dependency_links.txt
posix_pythonic_tool.egg-info/top_level.txt
ppt/__init__.py
ppt/eventloop.py