Metadata-Version: 1.2
Name: posix-pythonic-tool
Version: 0.0.1
Summary: posix-pythonic-tool
Home-page: https://github.com/Neeky/posix-pythonic-tool
Author: Neeky
Author-email: neeky@live.com
Maintainer: Neeky
Maintainer-email: neeky@live.com
License: UNKNOWN
Platform: UNKNOWN
Classifier: Operating System :: POSIX
Classifier: Operating System :: MacOS :: MacOS X
Classifier: Programming Language :: Python :: 3.6
Classifier: Programming Language :: Python :: 3.7
Classifier: Programming Language :: Python :: 3.8
Classifier: Programming Language :: Python :: 3.9
Requires-Python: >=3.6.*
